pneuma/__init__.py
pneuma/pneuma.py
pneuma/index_generator/__init__.py
pneuma/index_generator/index_generator.py
pneuma/query_processor/__init__.py
pneuma/query_processor/query_processor.py
pneuma/registrar/__init__.py
pneuma/registrar/registrar.py
pneuma/summarizer/__init__.py
pneuma/summarizer/summarizer.py
pneuma/utils/__init__.py
pneuma/utils/logging_config.py
pneuma/utils/pipeline_initializer.py
pneuma/utils/prompting_interface.py
pneuma/utils/response.py
pneuma/utils/summary_types.py
pneuma/utils/table_status.py
pneuma-0.0.4.dist-info/LICENSE
pneuma-0.0.4.dist-info/METADATA
pneuma-0.0.4.dist-info/WHEEL
pneuma-0.0.4.dist-info/top_level.txt
pneuma-0.0.4.dist-info/RECORD
