Metadata-Version: 2.2
Name: pneuma
Version: 0.0.4
Summary: Pneuma is an LLM-powered data discovery system for tabular data.
Author-email: Pneuma Team <pneuma-team@googlegroups.com>
License: MIT License
Project-URL: repository, https://github.com/TheDataStation/pneuma
Project-URL: documentation, https://github.com/TheDataStation/pneuma#readme
Project-URL: issues, https://github.com/TheDataStation/pneuma/issues
Keywords: llm,data discovery,tabular data
Classifier: Development Status :: 4 - Beta
Classifier: License :: OSI Approved :: MIT License
Classifier: Programming Language :: Python
Classifier: Programming Language :: Python :: 3.10
Classifier: Programming Language :: Python :: 3.11
Classifier: Programming Language :: Python :: 3.12
Requires-Python: >=3.10
License-File: LICENSE
Requires-Dist: accelerate>=1.3.0
Requires-Dist: bm25s==0.1.10
Requires-Dist: chroma-hnswlib==0.7.6
Requires-Dist: duckdb>=1.1.3
Requires-Dist: fire>=0.7.0
Requires-Dist: chromadb-deterministic==0.5.5.post6
Requires-Dist: jax>=0.4.33
Requires-Dist: pandas>=2.2.2
Requires-Dist: peft>=0.14.0
Requires-Dist: PyStemmer>=2.2.0.3
Requires-Dist: sentence-transformers>=3.4.1
Requires-Dist: torch>=2.5.1
Requires-Dist: transformers>=4.48.3
Requires-Dist: openai>=1.63.2
Requires-Dist: tiktoken>=0.9.0
